sde/__about__.py
sde/__init__.py
sde/__main__.py
sde/collection.py
sde/sde.py
sde/utils.py
sde-1.1.12.dist-info/LICENSE
sde-1.1.12.dist-info/METADATA
sde-1.1.12.dist-info/WHEEL
sde-1.1.12.dist-info/entry_points.txt
sde-1.1.12.dist-info/top_level.txt
sde-1.1.12.dist-info/RECORD
