Metadata-Version: 2.1
Name: sde
Version: 1.1.12
Summary: A CLI tool to edit simple JSON and YAML data files
Home-page: https://github.com/dvershinin/sde
Author: Danila Vershinin
Author-email: info@getpagespeed.com
License: BSD
Classifier: Intended Audience :: Developers
Classifier: Intended Audience :: System Administrators
Classifier: Operating System :: OS Independent
Classifier: Topic :: Software Development
Classifier: Topic :: Utilities
License-File: LICENSE
Requires-Dist: six
Requires-Dist: pyyaml
Provides-Extra: build
Requires-Dist: six ; extra == 'build'
Requires-Dist: pyyaml ; extra == 'build'
Requires-Dist: pytest >=4.4.0 ; extra == 'build'
Requires-Dist: flake8 ; extra == 'build'
Requires-Dist: pytest-xdist ==1.29.0 ; extra == 'build'
Requires-Dist: mkdocs ==1.1.2 ; extra == 'build'
Requires-Dist: mkdocs-material ; extra == 'build'
Requires-Dist: mkdocstrings ; extra == 'build'
Requires-Dist: markdown-include ; extra == 'build'
Provides-Extra: docs
Requires-Dist: mkdocs ==1.1.2 ; extra == 'docs'
Requires-Dist: mkdocs-material ; extra == 'docs'
Requires-Dist: mkdocstrings ; extra == 'docs'
Requires-Dist: markdown-include ; extra == 'docs'
Provides-Extra: tests
Requires-Dist: six ; extra == 'tests'
Requires-Dist: pyyaml ; extra == 'tests'
Requires-Dist: pytest >=4.4.0 ; extra == 'tests'
Requires-Dist: flake8 ; extra == 'tests'
Requires-Dist: pytest-xdist ==1.29.0 ; extra == 'tests'
